file_server_auto_https-0.2.0.dist-info/METADATA
file_server_auto_https-0.2.0.dist-info/WHEEL
file_server_auto_https-0.2.0.dist-info/entry_points.txt
file_server_auto_https-0.2.0.dist-info/licenses/LICENSE.txt
file_server_auto_https/__init__.py
file_server_auto_https/cli.py
file_server_auto_https/cloudflare/__init__.py
file_server_auto_https/cloudflare/client.py
file_server_auto_https/cloudflare/exceptions.py
file_server_auto_https/cmd/__init__.py
file_server_auto_https/cmd/cloudflare/__init__.py
file_server_auto_https/cmd/cloudflare/generate_dns_record.py
file_server_auto_https/cmd/server/serve.py
file_server_auto_https/lib/__init__.py
file_server_auto_https/lib/cloudflare/__init__.py
file_server_auto_https/lib/cloudflare/cloudflare_handler.py
file_server_auto_https/lib/grab_ip.py
file_server_auto_https/lib/server/file_server.py
file_server_auto_https/server/__init__.py
file_server_auto_https-0.2.0.dist-info/RECORD
