Metadata-Version: 2.1
Name: file-server-auto-https
Version: 0.2.0
Summary: File server with automatic HTTPS and Cloudflare DNS management
Author-Email: Tadeas Fort <business@tadeasfort.com>
License: GPL-3.0
Requires-Python: >=3.8
Requires-Dist: click>=8.1.7
Requires-Dist: python-dotenv>=1.0.1
Requires-Dist: requests>=2.31.0
Requires-Dist: pydantic>=2.5.0
Requires-Dist: rich>=13.7.0
Requires-Dist: shortuuid>=1.0.11
Requires-Dist: typer>=0.15.1
Provides-Extra: dev
Requires-Dist: pytest>=8.3.4; extra == "dev"
Requires-Dist: pytest-cov>=4.1.0; extra == "dev"
Requires-Dist: pytest-mock>=3.12.0; extra == "dev"
